<?xml version='1.1' encoding='UTF-8'?>
<com.cloudbees.plugins.credentials.SystemCredentialsProvider plugin="credentials@latest">
  <domainCredentialsMap class="hudson.util.CopyOnWriteMap$Hash">
    <entry>
      <com.cloudbees.plugins.credentials.domains.Domain>
        <specifications/>
      </com.cloudbees.plugins.credentials.domains.Domain>
      <java.util.concurrent.CopyOnWriteArrayList>
        <com.cloudbees.jenkins.plugins.awscredentials.AWSCredentialsImpl plugin="aws-credentials@latest">
          <scope>GLOBAL</scope>
          <id>aws_credentials</id>
          <description>Credentials for AWS</description>
          <accessKey>acces_key</accessKey>
          <secretKey>secret_key</secretKey>
          <iamRoleArn></iamRoleArn>
          <iamExternalId></iamExternalId>
          <iamMfaSerialNumber></iamMfaSerialNumber>
        </com.cloudbees.jenkins.plugins.awscredentials.AWSCredentialsImpl>
        <com.cloudbees.plugins.credentials.impl.UsernamePasswordCredentialsImpl>
          <scope>GLOBAL</scope>
          <id>github_credentials</id>
          <description>Credentials for GitHub</description>
          <username>MartinsLivca</username>
          <password>token</password>
          <usernameSecret>false</usernameSecret>
        </com.cloudbees.plugins.credentials.impl.UsernamePasswordCredentialsImpl>
      </java.util.concurrent.CopyOnWriteArrayList>
    </entry>
  </domainCredentialsMap>
</com.cloudbees.plugins.credentials.SystemCredentialsProvider>